cloudservice/__init__.py
cloudservice/cloud.py
cloudservice/slack_sender.py
cloudservice-0.20.0.dist-info/LICENSE
cloudservice-0.20.0.dist-info/METADATA
cloudservice-0.20.0.dist-info/WHEEL
cloudservice-0.20.0.dist-info/top_level.txt
cloudservice-0.20.0.dist-info/RECORD
