Metadata-Version: 2.1
Name: cloudservice
Version: 0.20.0
Summary: Auto machine learning, deep learning library in Python.
Home-page: https://github.com/tonne1997/cloudservice
Author: toandaominh1997
Author-email: toandaominh1997@gmail.com
License: MIT
Platform: UNKNOWN
Classifier: License :: OSI Approved :: MIT License
Classifier: Programming Language :: Python :: 3.7
Classifier: Programming Language :: Python :: 3.8
License-File: LICENSE
Requires-Dist: pandas
Requires-Dist: numpy
Requires-Dist: pandas-gbq
Requires-Dist: google-cloud-bigquery
Requires-Dist: google-cloud-storage
Requires-Dist: tqdm
Requires-Dist: gcsfs
